Metadata-Version: 2.1
Name: seperator
Version: 0.0.2
Summary: eye catching and informative seperator utilities for long shell client outputs
Home-page: https://github.com/eaybek/seperator
Author: Erdem Aybek
Author-email: eaybek@gmail.com
License: UNKNOWN
Platform: UNKNOWN
Classifier: Programming Language :: Python :: 3
Classifier: License :: OSI Approved :: MIT License
Classifier: Operating System :: OS Independent
Requires-Python: >=3.6
